LICENSE
MANIFEST.in
README
setup.py
django_subdomain.egg-info/PKG-INFO
django_subdomain.egg-info/SOURCES.txt
django_subdomain.egg-info/dependency_links.txt
django_subdomain.egg-info/not-zip-safe
django_subdomain.egg-info/top_level.txt
project/__init__.py
project/manage.py
project/settings.py
project/urls.py
project/subdomains/__init__.py
project/subdomains/context_processors.py
project/subdomains/decorators.py
project/subdomains/forms.py
project/subdomains/middleware.py
project/subdomains/models.py
project/subdomains/tests.py
project/subdomains/urls.py
project/subdomains/views.py
project/subdomains/conf/__init__.py
project/subdomains/conf/settings.py
subdomains/__init__.py
subdomains/context_processors.py
subdomains/decorators.py
subdomains/forms.py
subdomains/middleware.py
subdomains/models.py
subdomains/tests.py
subdomains/urls.py
subdomains/views.py
subdomains/conf/__init__.py
subdomains/conf/settings.py
subdomains/templates/subdomains/base.html
subdomains/templates/subdomains/create_subdomain.html